Metadata-Version: 2.4
Name: DjPractLelo
Version: 0.1.9
Summary: My first Python package
Author: DjPractVala
Author-email: DjPractVala <youremail@example.com>
License: MIT
Project-URL: Homepage, https://github.com/yourusername/my-package
Requires-Python: >=3.8
License-File: LICENCE
Dynamic: author
Dynamic: license-file
Dynamic: requires-python
